{
	"cmake" : 
	{
		"generator" : 
		{
			"multiConfig" : true,
			"name" : "Visual Studio 17 2022",
			"platform" : "x64"
		},
		"paths" : 
		{
			"cmake" : "D:/CMake/bin/cmake.exe",
			"cpack" : "D:/CMake/bin/cpack.exe",
			"ctest" : "D:/CMake/bin/ctest.exe",
			"root" : "D:/CMake/share/cmake-3.27"
		},
		"version" : 
		{
			"isDirty" : false,
			"major" : 3,
			"minor" : 27,
			"patch" : 0,
			"string" : "3.27.0-rc4",
			"suffix" : "rc4"
		}
	},
	"objects" : 
	[
		{
			"jsonFile" : "codemodel-v2-cdb0113fae074b6d9740.json",
			"kind" : "codemodel",
			"version" : 
			{
				"major" : 2,
				"minor" : 6
			}
		},
		{
			"jsonFile" : "cache-v2-c5b11432f0a0f36e4c95.json",
			"kind" : "cache",
			"version" : 
			{
				"major" : 2,
				"minor" : 0
			}
		},
		{
			"jsonFile" : "cmakeFiles-v1-e058a66d416e7e1c04d1.json",
			"kind" : "cmakeFiles",
			"version" : 
			{
				"major" : 1,
				"minor" : 0
			}
		},
		{
			"jsonFile" : "toolchains-v1-83746c2bbfa8efdea9f5.json",
			"kind" : "toolchains",
			"version" : 
			{
				"major" : 1,
				"minor" : 0
			}
		}
	],
	"reply" : 
	{
		"client-vscode" : 
		{
			"query.json" : 
			{
				"requests" : 
				[
					{
						"kind" : "cache",
						"version" : 2
					},
					{
						"kind" : "codemodel",
						"version" : 2
					},
					{
						"kind" : "toolchains",
						"version" : 1
					},
					{
						"kind" : "cmakeFiles",
						"version" : 1
					}
				],
				"responses" : 
				[
					{
						"jsonFile" : "cache-v2-c5b11432f0a0f36e4c95.json",
						"kind" : "cache",
						"version" : 
						{
							"major" : 2,
							"minor" : 0
						}
					},
					{
						"jsonFile" : "codemodel-v2-cdb0113fae074b6d9740.json",
						"kind" : "codemodel",
						"version" : 
						{
							"major" : 2,
							"minor" : 6
						}
					},
					{
						"jsonFile" : "toolchains-v1-83746c2bbfa8efdea9f5.json",
						"kind" : "toolchains",
						"version" : 
						{
							"major" : 1,
							"minor" : 0
						}
					},
					{
						"jsonFile" : "cmakeFiles-v1-e058a66d416e7e1c04d1.json",
						"kind" : "cmakeFiles",
						"version" : 
						{
							"major" : 1,
							"minor" : 0
						}
					}
				]
			}
		}
	}
}
